adjspecies3/__init__.py
adjspecies3/adjectives.txt
adjspecies3/nouns.txt
adjspecies3/species.txt
adjspecies3-0.1.4.dist-info/LICENSE.md
adjspecies3-0.1.4.dist-info/METADATA
adjspecies3-0.1.4.dist-info/WHEEL
adjspecies3-0.1.4.dist-info/entry_points.txt
adjspecies3-0.1.4.dist-info/top_level.txt
adjspecies3-0.1.4.dist-info/RECORD
