Metadata-Version: 2.1
Name: adjspecies3
Version: 0.1.4
Summary: 
